obpcreator/__init__.py
obpcreator/data_model.py
obpcreator/generate_BSE_scan_pattern.py
obpcreator/generate_build.py
obpcreator/point_infill_creation.py
obpcreator/simple_input.py
obpcreator/scanning_strategies/__init__.py
obpcreator/scanning_strategies/contour_strategies.py
obpcreator/scanning_strategies/infill_strategies.py
obpcreator/support_functions/__init__.py
obpcreator/support_functions/pv_mesh_manipulation.py
obpcreator/visualisation/__init__.py
obpcreator/visualisation/layer_vis.py
obpcreator/visualisation/point_geometry_2D_view.py
obpcreator/visualisation/point_vis.py
obpcreator/visualisation/pv_mesh_vis.py
obpcreator-0.0.12.dist-info/LICENSE
obpcreator-0.0.12.dist-info/METADATA
obpcreator-0.0.12.dist-info/WHEEL
obpcreator-0.0.12.dist-info/top_level.txt
obpcreator-0.0.12.dist-info/RECORD
