Metadata-Version: 2.1
Name: obpcreator
Version: 0.0.12
Summary: Generation of open beam path files based on different strategies
Author-email: Anton Wiberg <wiberg.anton@gmail.com>
License: Copyright (c) 2018 The Python Packaging Authority
Classifier: Programming Language :: Python :: 3
Classifier: License :: OSI Approved :: MIT License
Classifier: Operating System :: OS Independent
Requires-Python: >=3.7
License-File: LICENSE
Requires-Dist: svgpathtools
Requires-Dist: numpy
Requires-Dist: matplotlib
Requires-Dist: obplib
Requires-Dist: pyvista
Requires-Dist: shapely
Requires-Dist: pydantic
Requires-Dist: pytest
Requires-Dist: opencv-python
Requires-Dist: scipy
Requires-Dist: logbook
